{
    "@context": [
        "https://doi.org/10.5063/schema/codemeta-2.0",
        "http://schema.org"
    ],
    "softwareRequirements": {
        "@type": "SoftwareApplication",
        "identifier": "ucto",
        "name": "ucto",
        "version": ">= 0.28"
    },
	"funding": [
		{
			"@type": "Grant",
			"name": "CLARIN-NL (NWO grant 184.021.003)",
			"url": "https://www.clariah.nl",
            "funder": {
                "@type": "Organization",
                "name": "NWO", 
                "url": "https://www.nwo.nl"
            }
		},
		{
			"@type": "Grant",
			"name": "CLARIAH-CORE (NWO grant 184.033.101)",
			"url": "https://www.clariah.nl",
            "funder": {
                "@type": "Organization",
                "name": "NWO", 
                "url": "https://www.nwo.nl"
            }
        },
        {
            "@type": "Grant",
            "name": "CLARIAH-PLUS (NWO grant 184.034.023)",
            "funder": {
                "@type": "Organization",
                "name": "NWO", 
                "url": "https://www.nwo.nl"
            }
        }
	],
    "applicationCategory": [ "https://vocabs.dariah.eu/tadirah/annotating", "https://vocabs.dariah.eu/tadirah/tagging", "https://w3id.org/nwo-research-fields#Linguistics", "https://w3id.org/nwo-research-fields#TextualAndContentAnalysis" ],
	"developmentStatus": [ "https://www.repostatus.org/#active", "https://w3id.org/research-technology-readiness-levels#Level8Complete" ]
}
